MANIFEST.in
README.rst
setup.py
aliyun_python_sdk_teslamaxcompute.egg-info/PKG-INFO
aliyun_python_sdk_teslamaxcompute.egg-info/SOURCES.txt
aliyun_python_sdk_teslamaxcompute.egg-info/dependency_links.txt
aliyun_python_sdk_teslamaxcompute.egg-info/requires.txt
aliyun_python_sdk_teslamaxcompute.egg-info/top_level.txt
aliyunsdkteslamaxcompute/__init__.py
aliyunsdkteslamaxcompute/request/__init__.py
aliyunsdkteslamaxcompute/request/v20180104/GetClusterInstanceRequest.py
aliyunsdkteslamaxcompute/request/v20180104/GetInstancesStatusCountRequest.py
aliyunsdkteslamaxcompute/request/v20180104/GetProjectInstanceRequest.py
aliyunsdkteslamaxcompute/request/v20180104/GetQuotaHistoryInfoRequest.py
aliyunsdkteslamaxcompute/request/v20180104/GetQuotaInstanceRequest.py
aliyunsdkteslamaxcompute/request/v20180104/GetUserInstanceRequest.py
aliyunsdkteslamaxcompute/request/v20180104/ListUserQuotasRequest.py
aliyunsdkteslamaxcompute/request/v20180104/QueryCustomerSaleInfoRequest.py
aliyunsdkteslamaxcompute/request/v20180104/QueryResourceInventoryRequest.py
aliyunsdkteslamaxcompute/request/v20180104/QueryTopologyRequest.py
aliyunsdkteslamaxcompute/request/v20180104/__init__.py